CHANGES.md
MANIFEST.in
README.rst
setup.py
CosmoPhotoz/__init__.py
CosmoPhotoz/photoz.py
CosmoPhotoz/run_glm.py
CosmoPhotoz/test.py
CosmoPhotoz.egg-info/PKG-INFO
CosmoPhotoz.egg-info/SOURCES.txt
CosmoPhotoz.egg-info/dependency_links.txt
CosmoPhotoz.egg-info/requires.txt
CosmoPhotoz.egg-info/top_level.txt
CosmoPhotoz/data/PHAT0.csv.bz2