Metadata-Version: 1.1
Name: CosmoPhotoz
Version: 0.1
Summary: 
